spreadsheet_use/__init__.py
spreadsheet_use/py.typed
spreadsheet_use-0.1.2.dist-info/METADATA
spreadsheet_use-0.1.2.dist-info/WHEEL
spreadsheet_use-0.1.2.dist-info/licenses/LICENSE
spreadsheet_use-0.1.2.dist-info/RECORD
