Metadata-Version: 2.4
Name: spreadsheet-use
Version: 0.1.2
Summary: Spreadsheet Use: Alias package for univer-use
Project-URL: Homepage, https://github.com/dream-num/univer-use
Project-URL: Repository, https://github.com/dream-num/univer-use
Project-URL: Issues, https://github.com/dream-num/univer-use/issues
Author: Univer Team
License: MIT License
License-File: LICENSE
Keywords: agents,langchain,langgraph,mcp,spreadsheet,univer
Classifier: License :: OSI Approved :: MIT License
Classifier: Operating System :: OS Independent
Classifier: Programming Language :: Python :: 3
Classifier: Programming Language :: Python :: 3.11
Classifier: Programming Language :: Python :: 3.12
Classifier: Topic :: Software Development :: Libraries
Requires-Python: <4.0,>=3.11
Requires-Dist: univer-use==0.1.2
